nonebot_plugin_oddtext/__init__.py
nonebot_plugin_oddtext/bug.py
nonebot_plugin_oddtext/cxh.py
nonebot_plugin_oddtext/data_source.py
nonebot_plugin_oddtext/flip.py
nonebot_plugin_oddtext/hxw.py
nonebot_plugin_oddtext-0.2.1.dist-info/LICENSE
nonebot_plugin_oddtext-0.2.1.dist-info/METADATA
nonebot_plugin_oddtext-0.2.1.dist-info/WHEEL
nonebot_plugin_oddtext-0.2.1.dist-info/RECORD
